cythonflatiter/README.MD
cythonflatiter/__init__.py
cythonflatiter/requirements.txt
cythonflatiter/thirdparty.json
cythonflatiter-0.10.dist-info/LICENSE.rst
cythonflatiter-0.10.dist-info/METADATA
cythonflatiter-0.10.dist-info/WHEEL
cythonflatiter-0.10.dist-info/top_level.txt
cythonflatiter-0.10.dist-info/RECORD
