Metadata-Version: 2.1
Name: cythonflatiter
Version: 0.10
Summary: Locates values in NumPy Arrays with Cython
Home-page: https://github.com/hansalemaos/cythonflatiter
Author: Johannes Fischer
Author-email: aulasparticularesdealemaosp@gmail.com
License: MIT
Keywords: cython,arrays
Classifier: Development Status :: 4 - Beta
Classifier: Programming Language :: Python :: 3 :: Only
Classifier: Programming Language :: Python :: 3.10
Classifier: Topic :: Software Development :: Libraries :: Python Modules
Classifier: Topic :: Utilities
License-File: LICENSE.rst
Requires-Dist: Cython
Requires-Dist: cythonanyarray
Requires-Dist: numpy
